LICENSE
MANIFEST.in
README
setup.cfg
setup.py
docs/HISTORY.rst
docs/README.rst
docs/TODO.rst
docs/man/tonicdnscli.1
examples/example.org.txt
examples/tdclirc.sample
src/tests/__init__.py
src/tests/test__init__.py
src/tests/test_command.py
src/tests/test_connect.py
src/tests/test_converter.py
src/tests/test_pep8.py
src/tests/test_processing.py
src/tests/test_utils.py
src/tests/test_vars.py
src/tonicdnscli/__init__.py
src/tonicdnscli/command.py
src/tonicdnscli/connect.py
src/tonicdnscli/converter.py
src/tonicdnscli/processing.py
src/tonicdnscli/utils.py
src/tonicdnscli.egg-info/PKG-INFO
src/tonicdnscli.egg-info/SOURCES.txt
src/tonicdnscli.egg-info/dependency_links.txt
src/tonicdnscli.egg-info/entry_points.txt
src/tonicdnscli.egg-info/requires.txt
src/tonicdnscli.egg-info/top_level.txt