Metadata-Version: 1.1
Name: tonicdnscli
Version: 0.10
Summary: TonicDNS CLI tool
Home-page: https://github.com/mkouhei/tonicdnscli
Author: Kouhei Maeda
Author-email: mkouhei@palmtb.net
License:  GNU General Public License version 3
Platform: UNKNOWN
Classifier: Development Status :: 3 - Alpha
Classifier: Intended Audience :: System Administrators
Classifier: License :: OSI Approved :: GNU General Public License v3 or later (GPLv3+)
Classifier: Programming Language :: Python
Classifier: Topic :: Internet
Classifier: Topic :: Internet :: Name Service (DNS)
Classifier: Topic :: System :: Systems Administration
